ragops_agent_ce/__init__.py
ragops_agent_ce/__main__.py
ragops_agent_ce/agent/__init__.py
ragops_agent_ce/agent/agent.py
ragops_agent_ce/agent/local_tools/__init__.py
ragops_agent_ce/agent/local_tools/checklist_tools.py
ragops_agent_ce/agent/local_tools/project_tools.py
ragops_agent_ce/agent/local_tools/tools.py
ragops_agent_ce/agent/prompts.py
ragops_agent_ce/checklist_manager.py
ragops_agent_ce/cli.py
ragops_agent_ce/cli_helpers.py
ragops_agent_ce/command_palette.py
ragops_agent_ce/compose/services/docker-compose.yml
ragops_agent_ce/compose/templates/.env.template
ragops_agent_ce/compose/templates/README.md
ragops_agent_ce/config.py
ragops_agent_ce/credential_checker.py
ragops_agent_ce/db.py
ragops_agent_ce/display.py
ragops_agent_ce/http_client.py
ragops_agent_ce/interactive_input.py
ragops_agent_ce/llm/__init__.py
ragops_agent_ce/llm/provider_factory.py
ragops_agent_ce/llm/providers/__init__.py
ragops_agent_ce/llm/providers/mock.py
ragops_agent_ce/logging_config.py
ragops_agent_ce/mcp/client.py
ragops_agent_ce/mcp/servers/chunker_server.py
ragops_agent_ce/mcp/servers/compose_manager_server.py
ragops_agent_ce/mcp/servers/donkit_ragops_mcp.py
ragops_agent_ce/mcp/servers/planner_server.py
ragops_agent_ce/mcp/servers/rag_query_server.py
ragops_agent_ce/mcp/servers/read_engine_server.py
ragops_agent_ce/mcp/servers/vectorstore_loader_server.py
ragops_agent_ce/model_selector.py
ragops_agent_ce/prints.py
ragops_agent_ce/repl_helpers.py
ragops_agent_ce/schemas/agent_schemas.py
ragops_agent_ce/schemas/config_schemas.py
ragops_agent_ce/setup_wizard.py
ragops_agent_ce/supported_models.py
ragops_agent_ce/texts.py
donkit_ragops_ce-0.3.17.dist-info/LICENSE
donkit_ragops_ce-0.3.17.dist-info/METADATA
donkit_ragops_ce-0.3.17.dist-info/WHEEL
donkit_ragops_ce-0.3.17.dist-info/entry_points.txt
donkit_ragops_ce-0.3.17.dist-info/RECORD
