Metadata-Version: 2.3
Name: donkit-ragops-ce
Version: 0.3.17
Summary: Community Edition CLI agent for building RAG pipelines
License: MIT
Author: Donkit AI
Author-email: opensource@donkit.ai
Requires-Python: >=3.12,<3.14
Classifier: License :: OSI Approved :: MIT License
Classifier: Programming Language :: Python :: 3
Classifier: Programming Language :: Python :: 3.12
Classifier: Programming Language :: Python :: 3.13
Requires-Dist: donkit-chunker (>=0.1.4,<0.2.0)
Requires-Dist: donkit-embeddings (>=0.1.4,<0.2.0)
Requires-Dist: donkit-llm (>=0.1.4,<0.2.0)
Requires-Dist: donkit-ragops-api-gateway-client (>=0.1.5,<0.2.0)
Requires-Dist: donkit-read-engine (>=0.2.5,<0.3.0)
Requires-Dist: donkit-vectorstore-loader (>=0.1.7,<0.2.0)
Requires-Dist: fastmcp (>=2.13.0.2,<3.0.0.0)
Requires-Dist: google-genai (>=1.38.0,<2.0.0)
Requires-Dist: httpx (>=0.28.1,<0.29.0)
Requires-Dist: langchain (>=0.3.27,<0.4.0)
Requires-Dist: langchain-community (>=0.3.31,<0.4.0)
Requires-Dist: langchain-openai (>=0.3.35,<0.4.0)
Requires-Dist: loguru (>=0.7.3,<0.8.0)
Requires-Dist: nest-asyncio (>=1.6.0,<2.0.0)
Requires-Dist: openai (>=2.1.0,<3.0.0)
Requires-Dist: prompt-toolkit (>=3.0.48,<4.0.0)
Requires-Dist: pydantic (>=2.7.4,<3.0.0)
Requires-Dist: pydantic-settings (>=2.6.1,<3.0.0)
Requires-Dist: python-dotenv (>=1.0.1,<2.0.0)
Requires-Dist: rich (>=13.7.1,<14.0.0)
Requires-Dist: sqlmodel (>=0.0.16,<0.0.17)
Requires-Dist: typer (>=0.17.4,<0.18.0)
